ev/__init__.py
ev/py.typed
ev/cli/__init__.py
ev/cli/__main__.py
ev/cli/config.py
ev/cli/context.py
ev/cli/credentials.py
ev/cli/errors.py
ev/cli/project_config.py
ev/cli/validation.py
ev/cli/commands/__init__.py
ev/cli/commands/app.py
ev/cli/commands/cancel.py
ev/cli/commands/configure.py
ev/cli/commands/init.py
ev/cli/commands/list.py
ev/cli/commands/login.py
ev/cli/commands/result.py
ev/cli/commands/run.py
ev/client/__init__.py
ev/client/client.py
ev/git_utils/__init__.py
ev/inspect/__init__.py
ev/inspect/functions.py
ev/inspect/objects.py
ev/models/__init__.py
ev/runtime_env/__init__.py
ev/runtime_env/resolver.py
example/__init__.py
example/my_workflow.py
ev_sdk-0.1.5.dist-info/METADATA
ev_sdk-0.1.5.dist-info/WHEEL
ev_sdk-0.1.5.dist-info/entry_points.txt
ev_sdk-0.1.5.dist-info/top_level.txt
ev_sdk-0.1.5.dist-info/RECORD
