Metadata-Version: 2.4
Name: ev-sdk
Version: 0.1.5
Summary: The Python SDK for the EV Cloud.
Requires-Python: <3.13,>=3.10
Requires-Dist: click>=8.0.0
Requires-Dist: httpx>=0.28.1
Requires-Dist: pydantic>=2.11.7
Requires-Dist: requests>=2.32.5
Requires-Dist: rich>=14.1.0
Requires-Dist: websocket-client>=1.8.0
Requires-Dist: toml>=0.10.2
Requires-Dist: opentelemetry-sdk>=1.38.0
Requires-Dist: opentelemetry-exporter-otlp>=1.38.0
